sarkit-1.3.0.dist-info/METADATA
sarkit-1.3.0.dist-info/WHEEL
sarkit-1.3.0.dist-info/entry_points.txt
sarkit-1.3.0.dist-info/licenses/LICENSE
sarkit/__init__.py
sarkit/_constants.py
sarkit/_iohelp.py
sarkit/_processing/README.md
sarkit/_processing/__init__.py
sarkit/_processing/_sicd/__init__.py
sarkit/_processing/_sicd/deskew.py
sarkit/_processing/_sicd/pixel_type.py
sarkit/_processing/_sicd/subimage.py
sarkit/_version.py
sarkit/cphd/__init__.py
sarkit/cphd/_constants.py
sarkit/cphd/_cphdinfo.py
sarkit/cphd/_io.py
sarkit/cphd/_refgeom.py
sarkit/cphd/_xml.py
sarkit/cphd/schemas/CPHD_schema_V1.0.1_2018_05_21.xsd
sarkit/cphd/schemas/CPHD_schema_V1.1.0_2021_11_30_FINAL.xsd
sarkit/cphd/xsdtypes/CPHD_schema_V1.0.1_2018_05_21.json
sarkit/cphd/xsdtypes/CPHD_schema_V1.1.0_2021_11_30_FINAL.json
sarkit/crsd/__init__.py
sarkit/crsd/_computations.py
sarkit/crsd/_constants.py
sarkit/crsd/_crsdinfo.py
sarkit/crsd/_io.py
sarkit/crsd/_xml.py
sarkit/crsd/schemas/NGA.STND.0080-2_1.0_CRSD_schema_2025_02_25.xsd
sarkit/crsd/xsdtypes/NGA.STND.0080-2_1.0_CRSD_schema_2025_02_25.json
sarkit/py.typed
sarkit/sicd/__init__.py
sarkit/sicd/_constants.py
sarkit/sicd/_io.py
sarkit/sicd/_sicdinfo.py
sarkit/sicd/_xml.py
sarkit/sicd/projection/__init__.py
sarkit/sicd/projection/_calc.py
sarkit/sicd/projection/_derived.py
sarkit/sicd/projection/_errorprop.py
sarkit/sicd/projection/_params.py
sarkit/sicd/projection/_sensitivity.py
sarkit/sicd/schemas/SICD_schema_V1.1.0_2014_09_30.xsd
sarkit/sicd/schemas/SICD_schema_V1.2.1_2018_12_13.xsd
sarkit/sicd/schemas/SICD_schema_V1.3.0_2021_11_30.xsd
sarkit/sicd/schemas/SICD_schema_V1.4.0_2024_05_01.xsd
sarkit/sicd/xsdtypes/SICD_schema_V1.1.0_2014_09_30.json
sarkit/sicd/xsdtypes/SICD_schema_V1.2.1_2018_12_13.json
sarkit/sicd/xsdtypes/SICD_schema_V1.3.0_2021_11_30.json
sarkit/sicd/xsdtypes/SICD_schema_V1.4.0_2024_05_01.json
sarkit/sidd/__init__.py
sarkit/sidd/_constants.py
sarkit/sidd/_io.py
sarkit/sidd/_siddinfo.py
sarkit/sidd/_xml.py
sarkit/sidd/calculations/__init__.py
sarkit/sidd/calculations/coordinate_transformations.py
sarkit/sidd/calculations/exploitation_features.py
sarkit-1.3.0.dist-info/RECORD
