Metadata-Version: 2.1
Name: sarkit
Version: 1.3.0
Summary: Suite of SAR-related tools in Python.
Author-Email: Valkyrie Systems Corporation <info@govsco.com>
License: MIT
Classifier: Development Status :: 5 - Production/Stable
Classifier: Intended Audience :: Science/Research
Classifier: License :: OSI Approved :: MIT License
Classifier: Topic :: Scientific/Engineering
Classifier: Programming Language :: Python
Classifier: Programming Language :: Python :: 3
Classifier: Programming Language :: Python :: 3.11
Classifier: Programming Language :: Python :: 3.12
Classifier: Programming Language :: Python :: 3.13
Project-URL: Documentation, https://sarkit.readthedocs.io/
Project-URL: Repository, https://github.com/ValkyrieSystems/sarkit.git
Project-URL: Bug Tracker, https://github.com/ValkyrieSystems/sarkit/issues
Project-URL: Changelog, https://github.com/ValkyrieSystems/sarkit/blob/main/CHANGELOG.md
Requires-Python: >=3.11
Requires-Dist: jbpy<0.5,>=0.2.0
Requires-Dist: lxml>=5.1.0
Requires-Dist: numpy>=1.25.0
Requires-Dist: shapely>=2.0.2
Provides-Extra: verification
Provides-Extra: all
Provides-Extra: dev-lint
Requires-Dist: ruff>=0.3.0; extra == "dev-lint"
Requires-Dist: mypy>=1.8.0; extra == "dev-lint"
Provides-Extra: dev-test
Requires-Dist: aiohttp>=3.11; extra == "dev-test"
Requires-Dist: pytest>=7.4.4; extra == "dev-test"
Requires-Dist: smart_open[http]>=7.1.0; extra == "dev-test"
Requires-Dist: scipy>=1.12.0; extra == "dev-test"
Provides-Extra: dev
Requires-Dist: sarkit[dev-lint,dev-test]; extra == "dev"
